[
  {
    "action": "navigate",
    "url": "/students/{STUDENT_ID}/needs",
    "index": 1,
    "status": "passed",
    "durationMs": 1288,
    "screenshot": "reports\\3424266c\\step_01_after_nav.png"
  },
  {
    "action": "waitFor",
    "selector": "url: /students/{STUDENT_ID}/needs$",
    "index": 2,
    "status": "passed",
    "durationMs": 584,
    "screenshot": "reports\\3424266c\\step_02_after_wait.png"
  },
  {
    "action": "waitFor",
    "selector": "text: + New Needs Assessment",
    "index": 3,
    "status": "passed",
    "durationMs": 403,
    "screenshot": "reports\\3424266c\\step_03_after_wait.png"
  },
  {
    "action": "assertVisible",
    "selector": "text: + New Needs Assessment",
    "index": 4,
    "status": "passed",
    "durationMs": 417,
    "screenshot": "reports\\3424266c\\step_04_assert_visible.png"
  },
  {
    "action": "click",
    "selector": "text: + New Needs Assessment",
    "index": 5,
    "status": "passed",
    "durationMs": 401,
    "screenshot": "reports\\3424266c\\step_05_after_click.png"
  },
  {
    "action": "waitFor",
    "selector": "text: New Needs Assessment",
    "index": 6,
    "status": "passed",
    "durationMs": 458,
    "screenshot": "reports\\3424266c\\step_06_after_wait.png"
  },
  {
    "action": "type",
    "selector": "label: Academic Needs",
    "value": "pw_mcpreading_support_<timestamp>",
    "index": 7,
    "status": "passed",
    "durationMs": 487,
    "screenshot": "reports\\3424266c\\step_07_after_type.png"
  },
  {
    "action": "type",
    "selector": "label: Support Services",
    "value": "pw_mcptutoring_<timestamp>",
    "index": 8,
    "status": "passed",
    "durationMs": 399,
    "screenshot": "reports\\3424266c\\step_08_after_type.png"
  },
  {
    "action": "type",
    "selector": "label: Instructional Strategies",
    "value": "pw_mcpsmall_group_<timestamp>",
    "index": 9,
    "status": "passed",
    "durationMs": 421,
    "screenshot": "reports\\3424266c\\step_09_after_type.png"
  },
  {
    "action": "type",
    "selector": "label: Assessment Tools",
    "value": "pw_mcpmap_<timestamp>",
    "index": 10,
    "status": "passed",
    "durationMs": 379,
    "screenshot": "reports\\3424266c\\step_10_after_type.png"
  },
  {
    "action": "click",
    "selector": "text: Create",
    "index": 11,
    "status": "passed",
    "durationMs": 387,
    "screenshot": "reports\\3424266c\\step_11_after_click.png"
  },
  {
    "action": "waitFor",
    "selector": "text: <timestamp>",
    "index": 12,
    "status": "passed",
    "durationMs": 411,
    "screenshot": "reports\\3424266c\\step_12_after_wait.png"
  },
  {
    "action": "screenshot",
    "name": "needs_list_after_create",
    "index": 13,
    "status": "passed",
    "durationMs": 390,
    "screenshot": "reports\\3424266c\\step_13_needs_list_after_create.png"
  }
]